gtoolkit_tiktokenize/__init__.py
gtoolkit_tiktokenize/__version__.py
gtoolkit_tiktokenize/tokenize.py
gtoolkit_tiktokenize-0.1.7.dist-info/LICENSE
gtoolkit_tiktokenize-0.1.7.dist-info/WHEEL
gtoolkit_tiktokenize-0.1.7.dist-info/METADATA
gtoolkit_tiktokenize-0.1.7.dist-info/RECORD
