Metadata-Version: 2.1
Name: gtoolkit_tiktokenize
Version: 0.1.7
Summary: Glamorous Toolkit tiktoken wrapper
Author-email: feenk team <gt@feenk.com>
Requires-Python: >=3.8,<4
Classifier: License :: OSI Approved :: MIT License
Requires-Dist: tiktoken
Requires-Dist: gtoolkit_bridge
Project-URL: Home, https://gtoolkit.com
